coord2loc_usa/__init__.py
coord2loc_usa/py.typed
coord2loc_usa/data/__init__.py
coord2loc_usa/data/meta.msgpack
coord2loc_usa/data/polygons.msgpack
coord2loc_usa-0.0.1.dist-info/METADATA
coord2loc_usa-0.0.1.dist-info/WHEEL
coord2loc_usa-0.0.1.dist-info/entry_points.txt
coord2loc_usa-0.0.1.dist-info/RECORD
