Metadata-Version: 2.4
Name: coord2loc-usa
Version: 0.0.1
Summary: USA state outlines for coord2loc
Author-email: James Hale <james+coord2loc@hale.zip>
Requires-Python: >=3.9
Requires-Dist: coord2loc
